internacia/__init__.py
internacia/client.py
internacia/config.py
internacia/countries.py
internacia/database.py
internacia/downloader.py
internacia/exceptions.py
internacia/intblocks.py
internacia/models.py
internacia/py.typed
internacia/search.py
internacia/version.py
internacia-0.2.0.dist-info/licenses/LICENSE
internacia-0.2.0.dist-info/METADATA
internacia-0.2.0.dist-info/WHEEL
internacia-0.2.0.dist-info/top_level.txt
internacia-0.2.0.dist-info/RECORD
