Metadata-Version: 2.4
Name: internacia
Version: 0.2.0
Summary: Python SDK for accessing internacia-db data with support for countries, international blocks, and fuzzy search
Author: Dateno
Author-email: Dateno <ibegtin@dateno.io>
License: MIT
Project-URL: Homepage, https://github.com/commondataio/internacia-python
Project-URL: Documentation, https://github.com/commondataio/internacia-python#readme
Project-URL: Repository, https://github.com/commondataio/internacia-python
Project-URL: Issues, https://github.com/commondataio/internacia-python/issues
Keywords: countries,international-organizations,geography,data,sdk
Classifier: Development Status :: 4 - Beta
Classifier: Intended Audience :: Developers
Classifier: License :: OSI Approved :: MIT License
Classifier: Programming Language :: Python :: 3
Classifier: Programming Language :: Python :: 3.8
Classifier: Programming Language :: Python :: 3.9
Classifier: Programming Language :: Python :: 3.10
Classifier: Programming Language :: Python :: 3.11
Classifier: Programming Language :: Python :: 3.12
Classifier: Topic :: Software Development :: Libraries :: Python Modules
Classifier: Topic :: Scientific/Engineering :: Information Analysis
Requires-Python: >=3.8
License-File: LICENSE
Requires-Dist: duckdb>=0.9.0
Requires-Dist: pandas>=2.0.0
Requires-Dist: requests>=2.28.0
Provides-Extra: dev
Requires-Dist: pytest>=7.0.0; extra == "dev"
Requires-Dist: pytest-cov>=4.0.0; extra == "dev"
Requires-Dist: black>=23.0.0; extra == "dev"
Requires-Dist: ruff>=0.1.0; extra == "dev"
Requires-Dist: mypy>=1.0.0; extra == "dev"
Requires-Dist: pre-commit>=3.0.0; extra == "dev"
Provides-Extra: progress
Requires-Dist: tqdm>=4.64.0; extra == "progress"
Dynamic: author
Dynamic: license-file
Dynamic: requires-python
